CHANGES.txt
LICENSE.txt
MANIFEST.in
README.txt
setup.py
js/__init__.py
js.jquery_option_tree.egg-info/PKG-INFO
js.jquery_option_tree.egg-info/SOURCES.txt
js.jquery_option_tree.egg-info/dependency_links.txt
js.jquery_option_tree.egg-info/entry_points.txt
js.jquery_option_tree.egg-info/namespace_packages.txt
js.jquery_option_tree.egg-info/not-zip-safe
js.jquery_option_tree.egg-info/requires.txt
js.jquery_option_tree.egg-info/top_level.txt
js/jquery_option_tree/__init__.py
js/jquery_option_tree/test_jquery_option_tree.txt
js/jquery_option_tree/resources/jquery.optionTree.js
js/jquery_option_tree/resources/jquery.optionTree.min.js