Metadata-Version: 1.0
Name: js.jquery-option-tree
Version: 1.3
Summary: Fanstatic packaging of jquery-option-tree
Home-page: https://github.com/disko/js.jquery_option_tree
Author: Fanstatic Developers
Author-email: fanstatic@googlegroups.com
License: BSD
Platform: UNKNOWN
